Workbook

Sheet Spread Monitor
A1: US Treasury Spread Monitor — 2Y / 3Y / 10Y / 30Y
A2: Same layout as the KTB template · 1Y rolling window · compiled 2026-08-29 | L2: Percentile guide
A3: Security | B3: USGG2YR Index | C3: USGG3YR Index | D3: USGG10YR Index | E3: USGG30YR Index | F3: (on-the-run generics: GT2 Govt / GT3 Govt / GT10 Govt / GT30 Govt) | L3: 0.10 = lower 10% of past year (very flat)
A4: Start Date | B4: 45896 | L4: 0.25 = lower 25%
A5: End Date | B5: 46261 | L5: 0.50 = middle
A6: Source | B6: FRED daily constant-maturity yields DGS2/DGS3/DGS10/DGS30 (closes, through 2026-08-27). May differ from Bloomberg PX_LAST by 1-3bp. Aug 28 not yet included (see Verdict sheet). | L6: 0.80 = upper 20% (already steep)
L7: * Low spread = flat = steepener candidate; high = steep = flattener candidate
A8: Spread | C8: Current(bp) | D8: 1Y AVG | E8: STDEV.s | F8: Z-score | G8: Percentile | H8: 1M chg(bp) | I8: Vol(bp/d) | J8: Interpretation (1Y window)
A9: 2s10s | C9: =J24 | D9: =AVERAGE(J24:J274) | E9: =STDEV.S(J24:J274) | F9: =(C9-D9)/E9 | G9: =PERCENTRANK(J24:J274,C9) | H9: =J24-J45 | I9: =STDEV.S(R24:R273) | J9: =IF(G9<=0.1,"Lower 10% of past 1Y (very flat)",IF(G9<=0.25,"Lower 25% (flat side)",IF(G9<0.75,"Mid-range",IF(G9<0.9,"Upper 25% (steep side)","Upper 10% (already very steep)"))))
A10: 3s10s | C10: =L24 | D10: =AVERAGE(L24:L274) | E10: =STDEV.S(L24:L274) | F10: =(C10-D10)/E10 | G10: =PERCENTRANK(L24:L274,C10) | H10: =L24-L45 | I10: =STDEV.S(S24:S273) | J10: =IF(G10<=0.1,"Lower 10% of past 1Y (very flat)",IF(G10<=0.25,"Lower 25% (flat side)",IF(G10<0.75,"Mid-range",IF(G10<0.9,"Upper 25% (steep side)","Upper 10% (already very steep)"))))
A11: 10s30s | C11: =N24 | D11: =AVERAGE(N24:N274) | E11: =STDEV.S(N24:N274) | F11: =(C11-D11)/E11 | G11: =PERCENTRANK(N24:N274,C11) | H11: =N24-N45 | I11: =STDEV.S(T24:T273) | J11: =IF(G11<=0.1,"Lower 10% of past 1Y (very flat)",IF(G11<=0.25,"Lower 25% (flat side)",IF(G11<0.75,"Mid-range",IF(G11<0.9,"Upper 25% (steep side)","Upper 10% (already very steep)"))))
A12: 2s30s | C12: =P24 | D12: =AVERAGE(P24:P274) | E12: =STDEV.S(P24:P274) | F12: =(C12-D12)/E12 | G12: =PERCENTRANK(P24:P274,C12) | H12: =P24-P45 | I12: =STDEV.S(U24:U273) | J12: =IF(G12<=0.1,"Lower 10% of past 1Y (very flat)",IF(G12<=0.25,"Lower 25% (flat side)",IF(G12<0.75,"Mid-range",IF(G12<0.9,"Upper 25% (steep side)","Upper 10% (already very steep)"))))
A14: Daily-change correlation (1Y, in bp)
B15: 2Y | C15: 3Y | D15: 10Y | E15: 30Y | G15: Blue = data (paste new values) · Black = formulas · Yellow = key outputs
A16: 2Y | B16: =CORREL(C24:C273,C24:C273) | C16: =CORREL(C24:C273,E24:E273) | D16: =CORREL(C24:C273,G24:G273) | E16: =CORREL(C24:C273,I24:I273) | G16: If you add rows, extend the stat ranges (J24:J274 etc.) accordingly.
A17: 3Y | B17: =CORREL(E24:E273,C24:C273) | C17: =CORREL(E24:E273,E24:E273) | D17: =CORREL(E24:E273,G24:G273) | E17: =CORREL(E24:E273,I24:I273)
A18: 10Y | B18: =CORREL(G24:G273,C24:C273) | C18: =CORREL(G24:G273,E24:E273) | D18: =CORREL(G24:G273,G24:G273) | E18: =CORREL(G24:G273,I24:I273)
A19: 30Y | B19: =CORREL(I24:I273,C24:C273) | C19: =CORREL(I24:I273,E24:E273) | D19: =CORREL(I24:I273,G24:G273) | E19: =CORREL(I24:I273,I24:I273)
A20: vol (bp/day) | B20: =STDEV.S(C24:C273) | C20: =STDEV.S(E24:E273) | D20: =STDEV.S(G24:G273) | E20: =STDEV.S(I24:I273)
A22: Daily data (newest first) — all computed columns are formulas: insert new data on top and everything recalculates
A23: Date | B23: 2Y | C23: d2Y(bp) | D23: 3Y | E23: d3Y(bp) | F23: 10Y | G23: d10Y(bp) | H23: 30Y | I23: d30Y(bp) | J23: 2s10s(bp) | K23: Z 2s10s | L23: 3s10s(bp) | M23: Z 3s10s | N23: 10s30s(bp) | O23: Z 10s30s | P23: 2s30s(bp) | Q23: Z 2s30s | R23: d2s10s(bp) | S23: d3s10s(bp) | T23: d10s30s(bp) | U23: d2s30s(bp)
A24: 46261 | B24: 4.2 | C24: =(B24-B25)*100 | D24: 4.3 | E24: =(D24-D25)*100 | F24: 4.67 | G24: =(F24-F25)*100 | H24: 5.19 | I24: =(H24-H25)*100 | J24: =(F24-B24)*100 | K24: =(J24-$D$9)/$E$9 | L24: =(F24-D24)*100 | M24: =(L24-$D$10)/$E$10 | N24: =(H24-F24)*100 | O24: =(N24-$D$11)/$E$11 | P24: =(H24-B24)*100 | Q24: =(P24-$D$12)/$E$12 | R24: =J24-J25 | S24: =L24-L25 | T24: =N24-N25 | U24: =P24-P25
A25: 46260 | B25: 4.19 | C25: =(B25-B26)*100 | D25: 4.29 | E25: =(D25-D26)*100 | F25: 4.66 | G25: =(F25-F26)*100 | H25: 5.18 | I25: =(H25-H26)*100 | J25: =(F25-B25)*100 | K25: =(J25-$D$9)/$E$9 | L25: =(F25-D25)*100 | M25: =(L25-$D$10)/$E$10 | N25: =(H25-F25)*100 | O25: =(N25-$D$11)/$E$11 | P25: =(H25-B25)*100 | Q25: =(P25-$D$12)/$E$12 | R25: =J25-J26 | S25: =L25-L26 | T25: =N25-N26 | U25: =P25-P26
A26: 46259 | B26: 4.17 | C26: =(B26-B27)*100 | D26: 4.25 | E26: =(D26-D27)*100 | F26: 4.64 | G26: =(F26-F27)*100 | H26: 5.17 | I26: =(H26-H27)*100 | J26: =(F26-B26)*100 | K26: =(J26-$D$9)/$E$9 | L26: =(F26-D26)*100 | M26: =(L26-$D$10)/$E$10 | N26: =(H26-F26)*100 | O26: =(N26-$D$11)/$E$11 | P26: =(H26-B26)*100 | Q26: =(P26-$D$12)/$E$12 | R26: =J26-J27 | S26: =L26-L27 | T26: =N26-N27 | U26: =P26-P27
A27: 46258 | B27: 4.24 | C27: =(B27-B28)*100 | D27: 4.31 | E27: =(D27-D28)*100 | F27: 4.7 | G27: =(F27-F28)*100 | H27: 5.23 | I27: =(H27-H28)*100 | J27: =(F27-B27)*100 | K27: =(J27-$D$9)/$E$9 | L27: =(F27-D27)*100 | M27: =(L27-$D$10)/$E$10 | N27: =(H27-F27)*100 | O27: =(N27-$D$11)/$E$11 | P27: =(H27-B27)*100 | Q27: =(P27-$D$12)/$E$12 | R27: =J27-J28 | S27: =L27-L28 | T27: =N27-N28 | U27: =P27-P28
A28: 46255 | B28: 4.24 | C28: =(B28-B29)*100 | D28: 4.31 | E28: =(D28-D29)*100 | F28: 4.74 | G28: =(F28-F29)*100 | H28: 5.27 | I28: =(H28-H29)*100 | J28: =(F28-B28)*100 | K28: =(J28-$D$9)/$E$9 | L28: =(F28-D28)*100 | M28: =(L28-$D$10)/$E$10 | N28: =(H28-F28)*100 | O28: =(N28-$D$11)/$E$11 | P28: =(H28-B28)*100 | Q28: =(P28-$D$12)/$E$12 | R28: =J28-J29 | S28: =L28-L29 | T28: =N28-N29 | U28: =P28-P29
A29: 46254 | B29: 4.19 | C29: =(B29-B30)*100 | D29: 4.26 | E29: =(D29-D30)*100 | F29: 4.69 | G29: =(F29-F30)*100 | H29: 5.23 | I29: =(H29-H30)*100 | J29: =(F29-B29)*100 | K29: =(J29-$D$9)/$E$9 | L29: =(F29-D29)*100 | M29: =(L29-$D$10)/$E$10 | N29: =(H29-F29)*100 | O29: =(N29-$D$11)/$E$11 | P29: =(H29-B29)*100 | Q29: =(P29-$D$12)/$E$12 | R29: =J29-J30 | S29: =L29-L30 | T29: =N29-N30 | U29: =P29-P30
A30: 46253 | B30: 4.19 | C30: =(B30-B31)*100 | D30: 4.25 | E30: =(D30-D31)*100 | F30: 4.65 | G30: =(F30-F31)*100 | H30: 5.19 | I30: =(H30-H31)*100 | J30: =(F30-B30)*100 | K30: =(J30-$D$9)/$E$9 | L30: =(F30-D30)*100 | M30: =(L30-$D$10)/$E$10 | N30: =(H30-F30)*100 | O30: =(N30-$D$11)/$E$11 | P30: =(H30-B30)*100 | Q30: =(P30-$D$12)/$E$12 | R30: =J30-J31 | S30: =L30-L31 | T30: =N30-N31 | U30: =P30-P31
A31: 46252 | B31: 4.19 | C31: =(B31-B32)*100 | D31: 4.26 | E31: =(D31-D32)*100 | F31: 4.71 | G31: =(F31-F32)*100 | H31: 5.28 | I31: =(H31-H32)*100 | J31: =(F31-B31)*100 | K31: =(J31-$D$9)/$E$9 | L31: =(F31-D31)*100 | M31: =(L31-$D$10)/$E$10 | N31: =(H31-F31)*100 | O31: =(N31-$D$11)/$E$11 | P31: =(H31-B31)*100 | Q31: =(P31-$D$12)/$E$12 | R31: =J31-J32 | S31: =L31-L32 | T31: =N31-N32 | U31: =P31-P32
A32: 46251 | B32: 4.19 | C32: =(B32-B33)*100 | D32: 4.25 | E32: =(D32-D33)*100 | F32: 4.72 | G32: =(F32-F33)*100 | H32: 5.31 | I32: =(H32-H33)*100 | J32: =(F32-B32)*100 | K32: =(J32-$D$9)/$E$9 | L32: =(F32-D32)*100 | M32: =(L32-$D$10)/$E$10 | N32: =(H32-F32)*100 | O32: =(N32-$D$11)/$E$11 | P32: =(H32-B32)*100 | Q32: =(P32-$D$12)/$E$12 | R32: =J32-J33 | S32: =L32-L33 | T32: =N32-N33 | U32: =P32-P33
A33: 46248 | B33: 4.17 | C33: =(B33-B34)*100 | D33: 4.24 | E33: =(D33-D34)*100 | F33: 4.68 | G33: =(F33-F34)*100 | H33: 5.25 | I33: =(H33-H34)*100 | J33: =(F33-B33)*100 | K33: =(J33-$D$9)/$E$9 | L33: =(F33-D33)*100 | M33: =(L33-$D$10)/$E$10 | N33: =(H33-F33)*100 | O33: =(N33-$D$11)/$E$11 | P33: =(H33-B33)*100 | Q33: =(P33-$D$12)/$E$12 | R33: =J33-J34 | S33: =L33-L34 | T33: =N33-N34 | U33: =P33-P34
A34: 46247 | B34: 4.15 | C34: =(B34-B35)*100 | D34: 4.2 | E34: =(D34-D35)*100 | F34: 4.63 | G34: =(F34-F35)*100 | H34: 5.21 | I34: =(H34-H35)*100 | J34: =(F34-B34)*100 | K34: =(J34-$D$9)/$E$9 | L34: =(F34-D34)*100 | M34: =(L34-$D$10)/$E$10 | N34: =(H34-F34)*100 | O34: =(N34-$D$11)/$E$11 | P34: =(H34-B34)*100 | Q34: =(P34-$D$12)/$E$12 | R34: =J34-J35 | S34: =L34-L35 | T34: =N34-N35 | U34: =P34-P35
A35: 46246 | B35: 4.2 | C35: =(B35-B36)*100 | D35: 4.25 | E35: =(D35-D36)*100 | F35: 4.68 | G35: =(F35-F36)*100 | H35: 5.24 | I35: =(H35-H36)*100 | J35: =(F35-B35)*100 | K35: =(J35-$D$9)/$E$9 | L35: =(F35-D35)*100 | M35: =(L35-$D$10)/$E$10 | N35: =(H35-F35)*100 | O35: =(N35-$D$11)/$E$11 | P35: =(H35-B35)*100 | Q35: =(P35-$D$12)/$E$12 | R35: =J35-J36 | S35: =L35-L36 | T35: =N35-N36 | U35: =P35-P36
... A273: 45897 | B273: 3.62 | C273: =(B273-B274)*100 | D273: 3.6 | E273: =(D273-D274)*100 | F273: 4.22 | G273: =(F273-F274)*100 | H273: 4.88 | I273: =(H273-H274)*100 | J273: =(F273-B273)*100 | K273: =(J273-$D$9)/$E$9 | L273: =(F273-D273)*100 | M273: =(L273-$D$10)/$E$10 | N273: =(H273-F273)*100 | O273: =(N273-$D$11)/$E$11 | P273: =(H273-B273)*100 | Q273: =(P273-$D$12)/$E$12 | R273: =J273-J274 | S273: =L273-L274 | T273: =N273-N274 | U273: =P273-P274
A274: 45896 | B274: 3.59 | D274: 3.59 | F274: 4.24 | H274: 4.91 | J274: =(F274-B274)*100 | K274: =(J274-$D$9)/$E$9 | L274: =(F274-D274)*100 | M274: =(L274-$D$10)/$E$10 | N274: =(H274-F274)*100 | O274: =(N274-$D$11)/$E$11 | P274: =(H274-B274)*100 | Q274: =(P274-$D$12)/$E$12

Sheet Macro
A1: US Macro Dashboard — Jun / Jul / Aug 2026 (by data month)
A2: Release dates in notes · compiled 2026-08-29 · sources: BLS, BEA, CNBC, Advisor Perspectives, Axios, ISM, U.Michigan, Atlanta Fed
A4: INFLATION
A5: Indicator | B5: Metric | C5: Jun 2026 | D5: Jul 2026 | E5: Aug 2026 | F5: Notes
A6: CPI headline | B6: m/m | C6: -0.4% | D6: +0.1% | E6: due ~Sep 10 | F6: Jun: largest monthly drop since Apr 2020; beat 3.8% y/y consensus. Released Jul 14 / Aug 12.
B7: y/y | C7: 3.5% | D7: 3.4% | E7: — | F7: Peaked at 4.2% in May (Iran war / oil shock); easing but stuck in the 3s.
A8: Core CPI | B8: m/m | C8: 0.0% | D8: +0.2% | E8: due ~Sep 10 | F8: Core is well-behaved — the problem is energy.
B9: y/y | C9: 2.6% | D9: 2.5% | E9: —
A10: PCE headline | B10: m/m | C10: -0.1% | D10: +0.2% | E10: due late Sep | F10: Jul beat +0.1% consensus. Released Jul 31 / Aug 26.
B11: y/y | C11: 3.7% | D11: 3.7% | E11: — | F11: Eased from 4.1% in May, then stalled — disinflation paused.
A12: Core PCE | B12: m/m | C12: +0.1% | D12: +0.2% | E12: due late Sep
B13: y/y | C13: 3.3% | D13: 3.3% | E13: — | F13: Above 3.2% consensus; 1.3pp over the 2% target and going sideways — the hawks' key exhibit.
A14: PPI headline | B14: m/m | C14: +0.2% | D14: 0.0% | E14: due ~Sep 10 | F14: Jul flat vs +0.2% expected. Released Jul 15 / Aug 13.
B15: y/y | C15: 5.5% | D15: 4.7% | E15: — | F15: Down from 6.0% in May — pipeline pressure cooling fast.
A16: Core PPI | B16: m/m | C16: +0.4% | D16: +0.2% | E16: due ~Sep 10 | F16: Jul below 0.3% consensus.
B17: y/y | C17: 3.1% | D17: n/a* | E17: — | F17: *Jul y/y conflicting across sources (a reported 4.2% looks like the ex-food/energy/trade series) — verify on terminal.
A19: LABOR
A20: Indicator | B20: Metric | C20: Jun 2026 | D20: Jul 2026 | E20: Aug 2026 | F20: Notes
A21: Nonfarm payrolls | B21: k, m/m | C21: +57k -> revised +20k | D21: -23k (exp +80k) | E21: due Sep 4 | F21: Jul: first negative print; two-month revisions -103k. Released Jul 2 / Aug 7.
A22: Unemployment rate | B22: % | C22: 4.2% | D22: 4.1% | E22: due Sep 4 | F22: Fell for the wrong reason: participation 61.4%, a 5-year low (labor supply shrinking).
A23: Avg hourly earnings | B23: y/y | C23: — | D23: +3.2% | E23: due Sep 4 | F23: Slowest since May 2021 — wage-push pressure fading.
A24: ADP private payrolls | B24: k, m/m | C24: +95k (rev.) | D24: +44k (exp +70k) | E24: due Sep 2 | F24: Hiring slowdown confirmed.
A25: Initial jobless claims | B25: weekly | C25: ~190k | D25: low-200k | E25: 203k (wk Aug 22) | F25: Near 60-year lows — no layoffs; a hiring freeze, not a firing cycle.
A27: ACTIVITY & EXPECTATIONS
A28: Indicator | B28: Metric | C28: Jun 2026 | D28: Jul 2026 | E28: Aug 2026 | F28: Notes
A29: Retail sales | B29: m/m | C29: +0.2% (+6.7% y/y) | D29: -0.6% (+5.0% y/y) | E29: due mid-Sep | F29: Jul: biggest drop in over a year — consumer breather.
A30: ISM Manufacturing | B30: index | C30: 53.3 | D30: 55.6 | E30: due Sep 1 | F30: Jul highest since May 2022; Aug S&P flash mfg 53.2.
A31: ISM Services | B31: index | C31: 54.0 | D31: 54.1 | E31: due Sep 3 | F31: Aug S&P flash services 56.8, composite 56.0 (best since Apr 2022).
A32: Real GDP | B32: saar | C32: Q2 +1.5% | D32: — | E32: GDPNow Q3: 4.6% | F32: Q2 second estimate unchanged; consumption revised up to +3.4%. GDPNow as of Aug 26.
A33: U.Mich inflation exp. | B33: 1y / 5-10y | C33: 4.6% / 3.3% | D33: 4.2% / 3.3% | E33: 4.3% / 3.3% (prelim) | F33: Long-run expectations anchored at 3.3%; Aug sentiment 51.0.
A35: TAKEAWAY
A36: Inflation: headline stuck in the 3s, core PCE flat at 3.3% — no progress toward 2% since June.
A37: Labor: cooling sharply, but via shrinking supply (participation), not layoffs — claims near 60-yr lows.
A38: Activity: re-accelerating (GDPNow 4.6%, flash PMI 56.0, record-adjacent equities).
A39: Net: the Fed cannot cut (Sep 16 hike odds ~58% post-Jackson Hole); growth supports real yields; inflation uncertainty feeds the term premium.
A40: Event calendar: Sep 2 ADP · Sep 4 NFP · Sep 9 Treasury buybacks start · ~Sep 10 CPI/PPI · Sep 16 FOMC.

Sheet Verdict & Guide
A1: Spread Trade Verdict — data through 2026-08-27 (compiled 2026-08-29)
A3: Spread | B3: Current(bp) | C3: Z | D3: Pctile | E3: Verdict
A4: 3s10s | B4: ='Spread Monitor'!C10 | C4: ='Spread Monitor'!F10 | D4: ='Spread Monitor'!G10 | E4: Flattest of the past 1Y (12th pctile, z ~ -1.3) -> strongest statistical steepener candidate. Note the 3Y is the most sensitive point to Fed repricing.
A5: 10s30s | B5: ='Spread Monitor'!C11 | C5: ='Spread Monitor'!F11 | D5: ='Spread Monitor'!G11 | E5: 17th pctile, z ~ -1.0. Fiscal/supply argues steeper, but Treasury long-end buybacks from Sep 9 support the 30Y -> crosswinds.
A6: 2s30s | B6: ='Spread Monitor'!C12 | C6: ='Spread Monitor'!F12 | D6: ='Spread Monitor'!G12 | E6: 20th pctile, z ~ -0.8. Same direction, but highest vol (3.6bp/d) -> size accordingly.
A7: 2s10s | B7: ='Spread Monitor'!C9 | C7: ='Spread Monitor'!F9 | D7: ='Spread Monitor'!G9 | E7: 22nd pctile, z ~ -0.6 -> neutral-to-mild steepener. Signal not strong enough on its own.
A9: Overall verdict
A10: - All four spreads sit in the lower 12-22% of their 1Y range (flat side) — mean-reversion favors STEEPENERS, but |z| < 1.5, so "decent, not yet cheap".
A11: - The flattening has a clear cause: Warsh's hawkish Jackson Hole speech (Aug 28) pushed the 2Y to 4.34% and Sept hike odds from 35% to ~58% (CME). If a hike lands, bear-flattening can extend.
A12: - Note: Aug 28 closes (not yet in FRED data): 2Y 4.34 / 10Y 4.73 / 30Y 5.17 -> 2s10s ~39bp (z ~ -1.4), 10s30s ~44bp (z ~ -2.3, 1Y low) — better entry levels, bigger catalyst risk.
A13: - Execution: (1) scale in half before / half after the Sep 16 FOMC (2) be conservative on 10s30s steepeners until buybacks end (Sep 9 - Nov 4, >= $4bn per op) (3) stop-loss: z breaks below -2.5 or a genuine hiking cycle starts.
A15: Catalyst calendar
A16: Sep 2-4 labor data · Sep 9 buybacks start · ~Sep 10 CPI · Sep 16 FOMC (hike odds ~58%) · October refunding · Iran/oil, fiscal deficit (Jul $432bn), $739bn Q3 borrowing
A18: DV01-neutral hedge ratios (approximate — use terminal DV01 for execution)
A19: Tenor | B19: Approx duration | C19: DV01 / 100mm | D19: Steepener example vs 100mm 10Y short
A20: 2Y | B20: 1.9 | C20: =B20/100*10000 | D20: 2s10s: buy ~ 100mm x C22/C20 ~ 416mm of 2Y
A21: 3Y | B21: 2.8 | C21: =B21/100*10000 | D21: 3s10s: buy ~ 100mm x C22/C21 ~ 282mm of 3Y
A22: 10Y | B22: 7.9 | C22: =B22/100*10000 | D22: 10s30s: per 100mm 30Y short, buy ~ C23/C22 ~ 2.0x notional of 10Y
A23: 30Y | B23: 16 | C23: =B23/100*10000 | D23: (Approximations — vary with price/yield level)
A24: =BDH("USGG2YR Index","PX_LAST","8/27/2025","","Dir=V","Dts=S","Sort=D") <- Date + PX_LAST, vertical, newest first
A25: Tickers: USGG2YR / USGG3YR / USGG10YR / USGG30YR Index (generic yields) or GT2 / GT3 / GT10 / GT30 Govt. The US equivalent of KTB's GTKRW#YR Corp series is GT# Govt.
A26: Paste values into the blue columns (B/D/F/H) of the Spread Monitor sheet — spreads, Z-scores and percentiles all recalculate automatically.

Sheet Chart
A1: Spread history (bp, 1Y)
